dvpn/__init__.py
dvpn/__version__.py
dvpn/logger.py
dvpn/main.py
dvpn/make_qrc.py
dvpn/make_res.py
dvpn/res.py
dvpn/config/__init__.py
dvpn/config/constants.py
dvpn/config/paths.py
dvpn/modules/__init__.py
dvpn/modules/tools.py
dvpn/modules/vpn_cli_singleton.py
dvpn/vpns/__init__.py
dvpn/vpns/anyconnect.py
dvpn/vpns/base.py
dvpn/vpns/tunnelblick.py
dvpn/vpns/viscosity.py
dvpn-1.1.10.dist-info/LICENSE
dvpn-1.1.10.dist-info/METADATA
dvpn-1.1.10.dist-info/WHEEL
dvpn-1.1.10.dist-info/entry_points.txt
dvpn-1.1.10.dist-info/top_level.txt
dvpn-1.1.10.dist-info/zip-safe
dvpn-1.1.10.dist-info/RECORD
