Metadata-Version: 2.1
Name: dvpn
Version: 1.1.10
Summary: Tool for making life easy for people with more than one VPNs, with use of auto switching based on resolved hostnames and saved credentials
Home-page: https://github.com/jiri-otoupal/dievpn
Author: Jiri Otoupal
Author-email: jiri-otoupal@ips-database.eu
License: Apache 2.0
Keywords: DieVPN VPN Auto Resolver
Classifier: Development Status :: 4 - Beta
Classifier: Intended Audience :: Developers
Classifier: Programming Language :: Python :: 3.7
Classifier: Programming Language :: Python :: 3.8
Classifier: Programming Language :: Python :: 3.9
Classifier: Programming Language :: Python :: 3.10
Requires-Python: >=3.6,<4
License-File: LICENSE
Requires-Dist: click ==8.1.3
Requires-Dist: pyside6
Requires-Dist: pexpect ==4.8.0 ; sys_platform != "win32"
Requires-Dist: psutil ==5.9.4 ; sys_platform != "win32"
Requires-Dist: wexpect ==4.0.0 ; sys_platform == "win32"
Requires-Dist: psutil ==5.9.1 ; sys_platform == "win32"
Provides-Extra: dev
Requires-Dist: black ==22.* ; extra == 'dev'
